mcb/__init__.py
mcb-2.0.1.dist-info/AUTHORS
mcb-2.0.1.dist-info/LICENSE
mcb-2.0.1.dist-info/METADATA
mcb-2.0.1.dist-info/WHEEL
mcb-2.0.1.dist-info/pbr.json
mcb-2.0.1.dist-info/top_level.txt
mcb-2.0.1.dist-info/RECORD
